nmd/__init__.py
nmd/nmd.py
nmd/nmd_bow.py
nmd/nmd_index.py
nmd-0.0.6.dist-info/LICENSE
nmd-0.0.6.dist-info/WHEEL
nmd-0.0.6.dist-info/METADATA
nmd-0.0.6.dist-info/RECORD
