Metadata-Version: 2.1
Name: nmd
Version: 0.0.6
Summary: A string similarity measure based on the Earth Mover's Distance
Author-email: Avery Khoo <averykhoo@gmail.com>
Classifier: License :: OSI Approved :: MIT License
Project-URL: Home, https://github.com/averykhoo/ngram-movers-distance
